{
  "id": 389,
  "difficulty": "easy",
  "size": 7,
  "grid": [
    [
      " ",
      "#",
      " ",
      "#",
      "#",
      " ",
      " "
    ],
    [
      " ",
      " ",
      " ",
      " ",
      " ",
      " ",
      " "
    ],
    [
      " ",
      " ",
      " ",
      " ",
      " ",
      " ",
      " "
    ],
    [
      " ",
      " ",
      "#",
      " ",
      " ",
      " ",
      " "
    ],
    [
      " ",
      "#",
      " ",
      2,
      " ",
      " ",
      " "
    ],
    [
      " ",
      " ",
      " ",
      1,
      " ",
      " ",
      " "
    ],
    [
      " ",
      " ",
      " ",
      " ",
      " ",
      " ",
      " "
    ]
  ],
  "answer": [
    [
      1,
      2
    ],
    [
      0,
      6
    ],
    [
      3,
      5
    ],
    [
      5,
      0
    ],
    [
      6,
      3
    ],
    [
      4,
      4
    ],
    [
      2,
      1
    ],
    [
      4,
      2
    ]
  ]
}