{"grid":[[0,0,1,0,1,0,0,1,0,0],[0,0,0,0,0,0,0,0,0,1],[1,0,0,0,0,0,0,0,0,0],[0,0,0,1,0,0,0,1,0,0],[0,0,0,0,0,0,0,0,0,1],[0,0,1,0,0,0,0,0,0,0],[0,0,0,0,0,0,0,0,1,0],[1,0,1,0,1,0,0,0,0,0],[0,0,0,0,0,0,0,0,1,0],[0,0,0,0,0,1,0,0,0,0]],"size":10,"tents":{"8,9":true,"6,0":true,"2,1":true,"3,4":true,"0,5":true,"7,5":true,"8,2":true,"4,7":true,"5,3":true,"9,4":true,"0,1":true,"6,9":true,"1,7":true,"3,9":true,"0,9":true},"treeCount":15,"rowCounts":[3,1,1,2,1,1,2,1,2,1],"colCounts":[1,2,1,1,2,2,0,2,0,4],"unique":true,"id":"hard-0304","difficulty":"hard"}