{
  "size": 10,
  "row": 10,
  "col": 10,
  "holes": [
    1,
    10,
    12,
    15,
    17,
    33,
    36,
    37,
    38,
    43,
    47,
    56,
    61,
    78,
    81,
    89,
    93
  ],
  "answer": [
    97,
    96,
    95,
    94,
    93,
    92,
    91,
    90,
    80,
    81,
    82,
    83,
    84,
    85,
    86,
    87,
    88,
    98,
    99,
    89,
    79,
    69,
    59,
    49,
    39,
    29,
    19,
    9,
    8,
    18,
    28,
    38,
    48,
    58,
    68,
    78,
    77,
    76,
    75,
    74,
    73,
    72,
    71,
    70,
    60,
    50,
    40,
    30,
    20,
    10,
    0,
    1,
    2,
    3,
    4,
    5,
    6,
    7,
    17,
    27,
    37,
    47,
    57,
    67,
    66,
    65,
    64,
    63,
    62,
    61,
    51,
    41,
    31,
    21,
    11,
    12,
    13,
    14,
    15,
    16,
    26,
    25,
    24,
    23,
    22,
    32,
    42,
    52,
    53,
    43,
    33,
    34,
    44,
    54,
    55,
    56,
    46,
    36,
    35,
    45
  ],
  "difficulty": "hard",
  "id": 733
}