{
  "size": 10,
  "row": 10,
  "col": 10,
  "holes": [
    9,
    17,
    20,
    22,
    25,
    26,
    31,
    41,
    44,
    52,
    59,
    64,
    65,
    71,
    75,
    81,
    97,
    99
  ],
  "answer": [
    38,
    39,
    49,
    48,
    58,
    59,
    69,
    68,
    78,
    79,
    89,
    99,
    98,
    88,
    87,
    97,
    96,
    95,
    94,
    93,
    92,
    91,
    90,
    80,
    70,
    60,
    50,
    40,
    30,
    20,
    10,
    0,
    1,
    11,
    21,
    31,
    41,
    51,
    61,
    71,
    81,
    82,
    83,
    84,
    85,
    86,
    76,
    77,
    67,
    66,
    65,
    75,
    74,
    73,
    72,
    62,
    63,
    64,
    54,
    55,
    56,
    57,
    47,
    46,
    45,
    44,
    43,
    53,
    52,
    42,
    32,
    33,
    34,
    35,
    36,
    37,
    27,
    28,
    29,
    19,
    9,
    8,
    18,
    17,
    7,
    6,
    16,
    26,
    25,
    15,
    5,
    4,
    14,
    24,
    23,
    22,
    12,
    13,
    3,
    2
  ],
  "difficulty": "hard",
  "id": 705
}