{
  "size": 8,
  "row": 8,
  "col": 8,
  "holes": [
    41,
    42,
    43,
    44,
    45,
    46,
    49,
    50,
    51,
    52,
    53,
    54
  ],
  "answer": [
    27,
    28,
    29,
    37,
    36,
    35,
    34,
    26,
    18,
    19,
    20,
    21,
    13,
    12,
    4,
    5,
    6,
    7,
    15,
    14,
    22,
    23,
    31,
    30,
    38,
    39,
    47,
    55,
    63,
    62,
    61,
    60,
    59,
    58,
    57,
    56,
    48,
    40,
    32,
    33,
    25,
    24,
    16,
    17,
    9,
    8,
    0,
    1,
    2,
    3,
    11,
    10
  ],
  "difficulty": "medium",
  "id": 918
}