{
  "size": 8,
  "row": 8,
  "col": 8,
  "holes": [
    2,
    9,
    10,
    17,
    18,
    25,
    26,
    33,
    34,
    41,
    42,
    49,
    50
  ],
  "difficulty": "medium",
  "id": 431,
  "answer": [
    7,
    15,
    23,
    31,
    39,
    47,
    55,
    63,
    62,
    54,
    46,
    38,
    30,
    22,
    14,
    6,
    5,
    13,
    21,
    29,
    37,
    45,
    53,
    61,
    60,
    52,
    44,
    36,
    28,
    20,
    12,
    4,
    3,
    11,
    19,
    27,
    35,
    43,
    51,
    59,
    58,
    57,
    56,
    48,
    40,
    32,
    24,
    16,
    8,
    0,
    1
  ]
}