{
  "id": 32,
  "difficulty": "hard",
  "size": 12,
  "grid": [
    [
      0,
      0,
      0,
      0,
      0,
      0,
      0,
      0,
      0,
      0,
      0,
      0
    ],
    [
      0,
      0,
      0,
      0,
      0,
      0,
      0,
      0,
      0,
      0,
      0,
      0
    ],
    [
      0,
      0,
      0,
      0,
      0,
      0,
      0,
      0,
      0,
      0,
      0,
      0
    ],
    [
      0,
      0,
      1,
      0,
      0,
      0,
      0,
      0,
      0,
      0,
      0,
      0
    ],
    [
      0,
      0,
      0,
      0,
      0,
      0,
      0,
      0,
      0,
      1,
      0,
      0
    ],
    [
      0,
      0,
      1,
      0,
      0,
      0,
      0,
      0,
      3,
      0,
      1,
      0
    ],
    [
      0,
      0,
      0,
      0,
      2,
      0,
      0,
      0,
      0,
      0,
      2,
      0
    ],
    [
      0,
      0,
      0,
      0,
      0,
      0,
      0,
      0,
      0,
      0,
      1,
      0
    ],
    [
      0,
      0,
      0,
      0,
      0,
      2,
      0,
      0,
      2,
      0,
      0,
      0
    ],
    [
      0,
      0,
      0,
      0,
      0,
      0,
      0,
      0,
      0,
      0,
      0,
      0
    ],
    [
      0,
      0,
      0,
      1,
      0,
      0,
      0,
      0,
      0,
      0,
      2,
      0
    ],
    [
      0,
      0,
      2,
      0,
      0,
      0,
      0,
      0,
      0,
      0,
      0,
      0
    ]
  ],
  "answer": [
    [
      0,
      0
    ],
    [
      1,
      1
    ],
    [
      2,
      6
    ],
    [
      9,
      7
    ],
    [
      3,
      11
    ],
    [
      7,
      9
    ],
    [
      4,
      3
    ],
    [
      11,
      4
    ],
    [
      5,
      5
    ],
    [
      6,
      2
    ],
    [
      10,
      5
    ],
    [
      4,
      10
    ],
    [
      6,
      8
    ],
    [
      8,
      10
    ]
  ],
  "maxLights": 14
}