{
  "id": 40,
  "difficulty": "medium",
  "size": 10,
  "grid": [
    [
      0,
      0,
      0,
      0,
      0,
      0,
      0,
      0,
      1,
      2
    ],
    [
      0,
      0,
      0,
      0,
      0,
      0,
      0,
      0,
      0,
      0
    ],
    [
      0,
      0,
      0,
      0,
      2,
      0,
      0,
      0,
      0,
      0
    ],
    [
      0,
      0,
      0,
      0,
      0,
      1,
      0,
      0,
      0,
      0
    ],
    [
      2,
      0,
      0,
      0,
      0,
      0,
      0,
      0,
      0,
      0
    ],
    [
      0,
      0,
      0,
      0,
      0,
      0,
      0,
      0,
      0,
      0
    ],
    [
      0,
      0,
      0,
      0,
      0,
      0,
      0,
      0,
      0,
      0
    ],
    [
      0,
      0,
      0,
      0,
      0,
      0,
      0,
      0,
      0,
      0
    ],
    [
      0,
      0,
      0,
      0,
      0,
      0,
      0,
      0,
      1,
      0
    ],
    [
      0,
      0,
      0,
      0,
      0,
      0,
      0,
      0,
      0,
      0
    ]
  ],
  "answer": [
    [
      1,
      1
    ],
    [
      5,
      2
    ],
    [
      6,
      3
    ],
    [
      7,
      6
    ],
    [
      9,
      7
    ],
    [
      4,
      9
    ],
    [
      0,
      0
    ],
    [
      8,
      4
    ],
    [
      2,
      8
    ]
  ],
  "maxLights": 9
}