{
  "id": 19,
  "difficulty": "medium",
  "size": 10,
  "grid": [
    [
      " ",
      " ",
      " ",
      " ",
      " ",
      " ",
      " ",
      " ",
      " ",
      " "
    ],
    [
      " ",
      " ",
      " ",
      "#",
      " ",
      " ",
      " ",
      " ",
      " ",
      "#"
    ],
    [
      " ",
      " ",
      " ",
      " ",
      " ",
      " ",
      " ",
      " ",
      " ",
      " "
    ],
    [
      "#",
      " ",
      " ",
      " ",
      "#",
      " ",
      " ",
      " ",
      " ",
      " "
    ],
    [
      " ",
      " ",
      " ",
      " ",
      " ",
      " ",
      " ",
      " ",
      " ",
      " "
    ],
    [
      " ",
      3,
      " ",
      " ",
      1,
      " ",
      1,
      " ",
      " ",
      " "
    ],
    [
      " ",
      " ",
      " ",
      " ",
      "#",
      " ",
      " ",
      " ",
      " ",
      1
    ],
    [
      " ",
      " ",
      " ",
      1,
      " ",
      " ",
      1,
      " ",
      " ",
      " "
    ],
    [
      " ",
      " ",
      " ",
      " ",
      " ",
      " ",
      " ",
      " ",
      "#",
      "#"
    ],
    [
      " ",
      "#",
      "#",
      " ",
      " ",
      " ",
      " ",
      " ",
      " ",
      "#"
    ]
  ],
  "answer": [
    [
      6,
      6
    ],
    [
      1,
      5
    ],
    [
      2,
      7
    ],
    [
      9,
      3
    ],
    [
      5,
      0
    ],
    [
      4,
      1
    ],
    [
      7,
      2
    ],
    [
      8,
      4
    ],
    [
      0,
      8
    ],
    [
      3,
      9
    ],
    [
      7,
      9
    ],
    [
      1,
      0
    ],
    [
      6,
      1
    ],
    [
      5,
      3
    ]
  ]
}