{
  "id": 993,
  "difficulty": "medium",
  "size": 10,
  "grid": [
    [
      "#",
      " ",
      " ",
      " ",
      " ",
      " ",
      " ",
      " ",
      1,
      " "
    ],
    [
      " ",
      " ",
      " ",
      " ",
      " ",
      " ",
      " ",
      " ",
      " ",
      " "
    ],
    [
      " ",
      " ",
      " ",
      " ",
      " ",
      " ",
      " ",
      1,
      " ",
      " "
    ],
    [
      " ",
      " ",
      " ",
      " ",
      " ",
      " ",
      " ",
      " ",
      "#",
      " "
    ],
    [
      " ",
      " ",
      " ",
      " ",
      " ",
      " ",
      " ",
      " ",
      " ",
      " "
    ],
    [
      " ",
      " ",
      " ",
      " ",
      " ",
      " ",
      "#",
      " ",
      "#",
      " "
    ],
    [
      " ",
      " ",
      " ",
      " ",
      " ",
      " ",
      " ",
      " ",
      "#",
      " "
    ],
    [
      " ",
      " ",
      " ",
      " ",
      " ",
      1,
      " ",
      " ",
      "#",
      " "
    ],
    [
      " ",
      "#",
      " ",
      " ",
      " ",
      " ",
      " ",
      " ",
      " ",
      1
    ],
    [
      1,
      " ",
      "#",
      " ",
      " ",
      " ",
      " ",
      " ",
      " ",
      "#"
    ]
  ],
  "answer": [
    [
      2,
      3
    ],
    [
      6,
      4
    ],
    [
      7,
      9
    ],
    [
      1,
      8
    ],
    [
      3,
      7
    ],
    [
      5,
      0
    ],
    [
      8,
      5
    ],
    [
      9,
      6
    ],
    [
      4,
      1
    ],
    [
      0,
      2
    ],
    [
      9,
      1
    ]
  ]
}